setup.py
aljpy/__init__.py
aljpy/arrdict.py
aljpy/cache.py
aljpy/debugging.py
aljpy/dotdict.py
aljpy/download.py
aljpy/email.py
aljpy/humanhash.py
aljpy/humanhashadjectives.txt
aljpy/humanhashnouns.txt
aljpy/log.py
aljpy/notify.py
aljpy/parallel.py
aljpy/plot.py
aljpy/recording.py
aljpy/timer.py
aljpy/webarchive.py
aljpy/wiki.py
aljpy.egg-info/PKG-INFO
aljpy.egg-info/SOURCES.txt
aljpy.egg-info/dependency_links.txt
aljpy.egg-info/requires.txt
aljpy.egg-info/top_level.txt