Metadata-Version: 1.0
Name: aljpy
Version: 0.7
Summary: Andy's common tools
Home-page: https://github.com/andyljones/aljpy
Author: Andy Jones
Author-email: andyjones.ed@gmail.com
License: UNKNOWN
Platform: UNKNOWN
